{
  "data": [
    {
      "name": "react-native-draftjs-render",
      "desc": "React Native render for draft.js model",
      "site": null,
      "url": "https://github.com/globocom/react-native-draftjs-render",
      "pushedAt": "2018-07-03T19:12:13Z",
      "owner": {
        "avatar": "https://avatars2.githubusercontent.com/u/83798?v=4",
        "url": "https://github.com/globocom",
        "login": "globocom"
      },
      "stars": 236,
      "issues": 1,
      "release": [
        {
          "update": "2018-03-18T01:56:53Z",
          "name": "",
          "pre": false,
          "url": "https://github.com/globocom/react-native-draftjs-render/releases/tag/v2.7.0"
        }
      ],
      "topics": [
        "reactnative",
        "draftjs",
        "react-native",
        "draft-js"
      ],
      "tags": [
        {
          "name": "v2.8.2"
        }
      ]
    },
    {
      "name": "react-native-html-to-pdf",
      "desc": "Convert html strings to PDF documents using React Native",
      "site": null,
      "url": "https://github.com/christopherdro/react-native-html-to-pdf",
      "pushedAt": "2018-07-25T13:27:08Z",
      "owner": {
        "avatar": "https://avatars2.githubusercontent.com/u/3741055?v=4",
        "url": "https://github.com/christopherdro",
        "login": "christopherdro"
      },
      "stars": 161,
      "issues": 16,
      "release": [],
      "topics": [],
      "tags": [
        {
          "name": "v0.6.0"
        }
      ]
    },
    {
      "name": "react-native-htmltext",
      "desc": "Use HTML like markup to create stylized text in ReactNative.",
      "site": null,
      "url": "https://github.com/siuying/react-native-htmltext",
      "pushedAt": "2017-08-08T04:32:06Z",
      "owner": {
        "avatar": "https://avatars3.githubusercontent.com/u/8608?v=4",
        "url": "https://github.com/siuying",
        "login": "siuying"
      },
      "stars": 132,
      "issues": 4,
      "release": [],
      "topics": [],
      "tags": []
    },
    {
      "name": "react-native-html-webview",
      "desc": "Display HTML in a UIWebView, optionally sanitizing it first",
      "site": null,
      "url": "https://github.com/almost/react-native-html-webview",
      "pushedAt": "2016-05-31T18:18:46Z",
      "owner": {
        "avatar": "https://avatars0.githubusercontent.com/u/11125?v=4",
        "url": "https://github.com/almost",
        "login": "almost"
      },
      "stars": 103,
      "issues": 4,
      "release": [],
      "topics": [],
      "tags": []
    },
    {
      "name": "react-native-html-render",
      "desc": "A html render for react-native",
      "site": null,
      "url": "https://github.com/soliury/react-native-html-render",
      "pushedAt": "2017-12-18T11:38:17Z",
      "owner": {
        "avatar": "https://avatars0.githubusercontent.com/u/5032079?v=4",
        "url": "https://github.com/soliury",
        "login": "soliury"
      },
      "stars": 97,
      "issues": 9,
      "release": [],
      "topics": [
        "noder",
        "react-native",
        "react"
      ],
      "tags": [
        {
          "name": "v1.0.5"
        }
      ]
    },
    {
      "name": "react-native-measure-text",
      "desc": "Measure text width and/or height without laying it out.",
      "site": "",
      "url": "https://github.com/airamrguez/react-native-measure-text",
      "pushedAt": "2018-05-27T10:39:02Z",
      "owner": {
        "avatar": "https://avatars1.githubusercontent.com/u/1159448?v=4",
        "url": "https://github.com/airamrguez",
        "login": "airamrguez"
      },
      "stars": 41,
      "issues": 4,
      "release": [],
      "topics": [
        "react-native",
        "measue",
        "text",
        "height"
      ],
      "tags": []
    },
    {
      "name": "react-native-hypertext",
      "desc": "React Native module to render hypertext (text with links)",
      "site": null,
      "url": "https://github.com/agentcooper/react-native-hypertext",
      "pushedAt": "2016-06-13T19:22:59Z",
      "owner": {
        "avatar": "https://avatars0.githubusercontent.com/u/794591?v=4",
        "url": "https://github.com/agentcooper",
        "login": "agentcooper"
      },
      "stars": 20,
      "issues": 1,
      "release": [],
      "topics": [],
      "tags": []
    },
    {
      "name": "react-native-asciimage",
      "desc": "An <ASCIImage /> component for React Native",
      "site": "http://asciimage.org/",
      "url": "https://github.com/turley/react-native-asciimage",
      "pushedAt": "2015-08-06T00:09:09Z",
      "owner": {
        "avatar": "https://avatars0.githubusercontent.com/u/309021?v=4",
        "url": "https://github.com/turley",
        "login": "turley"
      },
      "stars": 16,
      "issues": 0,
      "release": [],
      "topics": [],
      "tags": []
    },
    {
      "name": "react-native-universal-modal",
      "desc": "Universal simple modal component for React Native",
      "site": "",
      "url": "https://github.com/bokuweb/react-native-universal-modal",
      "pushedAt": "2016-01-24T03:32:05Z",
      "owner": {
        "avatar": "https://avatars0.githubusercontent.com/u/10220449?v=4",
        "url": "https://github.com/bokuweb",
        "login": "bokuweb"
      },
      "stars": 16,
      "issues": 0,
      "release": [],
      "topics": [
        "react-native"
      ],
      "tags": []
    },
    {
      "name": "react-native-responsive-fontSize",
      "desc": "🔠 Responsive fontSize based on screen-size of the device in React-Native",
      "site": "",
      "url": "https://github.com/heyman333/react-native-responsive-fontSize",
      "pushedAt": "2018-05-10T08:14:34Z",
      "owner": {
        "avatar": "https://avatars1.githubusercontent.com/u/22214150?v=4",
        "url": "https://github.com/heyman333",
        "login": "heyman333"
      },
      "stars": 11,
      "issues": 0,
      "release": [],
      "topics": [
        "react",
        "react-native",
        "font",
        "fontsize",
        "reponsive",
        "git",
        "github"
      ],
      "tags": []
    }
  ],
  "modifiedOn": "2018-07-31T12:37:25.714Z"
}